remote_debugging_path_chromium/chromium.py
remote_debugging_path_chromium-0.1.0.dist-info/LICENSE
remote_debugging_path_chromium-0.1.0.dist-info/METADATA
remote_debugging_path_chromium-0.1.0.dist-info/WHEEL
remote_debugging_path_chromium-0.1.0.dist-info/entry_points.txt
remote_debugging_path_chromium-0.1.0.dist-info/top_level.txt
remote_debugging_path_chromium-0.1.0.dist-info/RECORD
