Metadata-Version: 2.1
Name: remote-debugging-path-chromium
Version: 0.1.0
Summary: UNIX domain path proxy for Chromium's remote debugging tools
Home-page: https://github.com/rianhunter/remote_debugging_path_chromium
Author: Rian Hunter
Author-email: rian@alum.mit.edu
License: GPL3
Platform: UNKNOWN
Requires-Dist: aiohttp
